tether/__init__.py
tether/functional/__init__.py
tether/functional/alif.py
tether/functional/lif.py
tether/functional/plif.py
tether/kernels/__init__.py
tether/kernels/alif.py
tether/kernels/attention.py
tether/kernels/encoding.py
tether/kernels/lif.py
tether/kernels/linear_lif.py
tether/kernels/plif.py
tether/nn/__init__.py
tether/nn/alif.py
tether/nn/attention.py
tether/nn/block.py
tether/nn/lif.py
tether/nn/linear_lif.py
tether/nn/plif.py
tether/nn/surrogates.py
tether/utils/monitor.py
tetherpy-0.2.0.dist-info/METADATA
tetherpy-0.2.0.dist-info/WHEEL
tetherpy-0.2.0.dist-info/licenses/LICENSE
tetherpy-0.2.0.dist-info/RECORD
