Metadata-Version: 2.4
Name: tetherpy
Version: 0.2.0
Summary: Triton-powered framework for training and deploying Spiking Transformers.
License-File: LICENSE
Requires-Python: >=3.10
Requires-Dist: numpy
Requires-Dist: torch
Requires-Dist: torchvision>=0.24.1
Requires-Dist: triton
Provides-Extra: dev
Requires-Dist: gputil>=1.4.0; extra == 'dev'
Requires-Dist: psutil>=7.2.1; extra == 'dev'
Requires-Dist: pytest-cov>=7.0.0; extra == 'dev'
Requires-Dist: pytest>=9.0.2; extra == 'dev'
Requires-Dist: snntorch>=0.9.4; extra == 'dev'
Requires-Dist: spikingjelly>=0.0.0.0.14; extra == 'dev'
Provides-Extra: docs
Requires-Dist: furo>=2025.9.25; extra == 'docs'
Requires-Dist: myst-parser>=4.0.1; extra == 'docs'
Requires-Dist: ruff>=0.14.10; extra == 'docs'
Requires-Dist: sphinx-autodoc-typehints>=3.0.1; extra == 'docs'
Requires-Dist: sphinx-rtd-theme>=3.0.0; extra == 'docs'
Requires-Dist: sphinx>=8.1.3; extra == 'docs'
